kryptk/__init__.py
kryptk/files_operations.py
kryptk/global_params.py
kryptk/interfaces.py
kryptk/main.py
kryptk/pyca_fernet.py
kryptk/utils.py
kryptk-0.0.3.dist-info/LICENSE
kryptk-0.0.3.dist-info/METADATA
kryptk-0.0.3.dist-info/WHEEL
kryptk-0.0.3.dist-info/top_level.txt
kryptk-0.0.3.dist-info/RECORD
