Metadata-Version: 2.1
Name: kryptk
Version: 0.0.3
Summary: Some ciphers implementation.
Author-email: The220th <The220th@gmail.com>
Project-URL: Homepage, https://github.com/The220th/kryptk
Project-URL: Issues, https://github.com/The220th/kryptk/issues
Classifier: Programming Language :: Python :: 3
Classifier: License :: OSI Approved :: MIT License
Classifier: Operating System :: OS Independent
Requires-Python: >=3.7
License-File: LICENSE
Requires-Dist: ksupk
Requires-Dist: cryptography
Requires-Dist: tqdm
